osm_data_client/__init__.py
osm_data_client/__version__.py
osm_data_client/cli.py
osm_data_client/client.py
osm_data_client/exceptions.py
osm_data_client/models.py
osm_data_client/processing.py
osm_data_client/utils/__init__.py
osm_data_client/utils/file.py
osm_data_client/utils/geometry.py
raw_data_api_py-0.3.0.dist-info/METADATA
raw_data_api_py-0.3.0.dist-info/WHEEL
raw_data_api_py-0.3.0.dist-info/licenses/LICENSE.md
raw_data_api_py-0.3.0.dist-info/RECORD
