Metadata-Version: 2.4
Name: raw-data-api-py
Version: 0.3.0
Summary: A Python API wrapper for the raw-data-api service.
License-File: LICENSE.md
Requires-Python: >=3.10
Requires-Dist: aiofiles>=24.1.0
Requires-Dist: aiohttp>=3.8.0
Requires-Dist: stream-unzip>=0.0.99
